{
  "data": [
    {
      "name": "Первый человек",
      "original_name": "First Man",
      "alternative_name": null,
      "year": 2017,
      "id_kp": 1092770,
      "alternative_id_kp": null,
      "id_imdb": "tt7027210",
      "id_tmdb": 432320,
      "id_world_art": null,
      "token_movie": "7abbc9ff8d5d8be5476436a379b020",
      "last_season": null,
      "last_episode": null,
      "date": "2021-04-10 18:20:28",
      "country": "США",
      "category": "Фильм",
      "genre": "документальный",
      "actors": "Nadine Adams, Jason Barnard, Фред Боббитт, Lee-Shane Booysen, Danica Carelse, Jacobus Claassen, Amir Gelgor, Nieke Lombard, Дмитрий Лоув, Octavia Meissenheimer, Эдриэнн Пирс, Ashley Robinson, Daniel Robinson, Свен Райгрок, Richard September, Anathe Shand, Нкосентша Тамана, Амброзе Арен, Натали Уолш, Нэйтан Уиллкокс",
      "directors": "Фред Фюжа, Джером Гио",
      "producers": "Арно де Баттис, Patricia Boutinard Rouelle, Бартелеми Фюжа",
      "premiere_ru": null,
      "premiere": "2017-06-08",
      "age_restrictions": null,
      "rating_mpaa": null,
      "rating_kp": null,
      "rating_imdb": 6.7,
      "time": "01:32",
      "tagline": null,
      "poster": "https://kinopoiskapiunofficial.tech/images/posters/kp/1092770.jpg",
      "description": null,
      "iframe": "",
      "iframe_trailer": "https://miyagi.allohastream.com/t/?token_movie=7abbc9ff8d5d8be5476436a379b020&token=",
      "category_id": 1,
      "quality": "WEB-DL",
      "translation": "Многоголосый закадровый",
      "translation_iframe": {
        "72": {
          "name": "Многоголосый закадровый",
          "quality": "WEB-DL",
          "iframe": "",
          "adv": true
        }
      }
    },
    {
      "name": "Знаменит в Японии",
      "original_name": "Big in Japan",
      "alternative_name": null,
      "year": 2019,
      "id_kp": null,
      "alternative_id_kp": null,
      "id_imdb": "tt6970798",
      "id_tmdb": 496668,
      "id_world_art": null,
      "token_movie": "703d2e111f4a92409bad8ebb1f688c",
      "last_season": null,
      "last_episode": null,
      "date": "2021-04-10 18:20:14",
      "country": null,
      "category": "Фильм",
      "genre": null,
      "actors": null,
      "directors": null,
      "producers": null,
      "premiere_ru": null,
      "premiere": null,
      "age_restrictions": null,
      "rating_mpaa": null,
      "rating_kp": null,
      "rating_imdb": null,
      "time": null,
      "tagline": null,
      "poster": null,
      "description": null,
      "iframe": "",
      "iframe_trailer": null,
      "category_id": 1,
      "quality": "WEB-DL",
      "translation": "Многоголосый закадровый",
      "translation_iframe": {
        "72": {
          "name": "Многоголосый закадровый",
          "quality": "WEB-DL",
          "iframe": "",
          "adv": true
        }
      }
    },
    {
      "name": "Массив любви ",
      "original_name": "Bikdeiteo yeonae",
      "alternative_name": "База данных свиданий",
      "year": 2019,
      "id_kp": 1325501,
      "alternative_id_kp": null,
      "id_imdb": null,
      "id_tmdb": null,
      "id_world_art": null,
      "token_movie": "68fafa403524d66c360409648aac65",
      "last_season": null,
      "last_episode": null,
      "date": "2021-04-10 18:19:30",
      "country": "Корея Южная",
      "category": "Фильм",
      "genre": "комедия, мелодрама",
      "actors": "Сон Джэ-рим, Чон Со-мин, Ли Сун-вон",
      "directors": "",
      "producers": "",
      "premiere_ru": null,
      "premiere": "2019-12-25",
      "age_restrictions": null,
      "rating_mpaa": null,
      "rating_kp": null,
      "rating_imdb": null,
      "time": "01:10",
      "tagline": null,
      "poster": "https://kinopoiskapiunofficial.tech/images/posters/kp/1325501.jpg",
      "description": "Разработчик мобильных приложений, который верит только цифрам, внезапно влюбляется.",
      "iframe": "",
      "iframe_trailer": null,
      "category_id": 1,
      "quality": "WEB-DL",
      "translation": "Многоголосый закадровый",
      "translation_iframe": {
        "72": {
          "name": "Многоголосый закадровый",
          "quality": "WEB-DL",
          "iframe": "",
          "adv": true
        }
      }
    },
    {
      "name": "Насекомые: Трилогия",
      "original_name": "Bugs: A Trilogy",
      "alternative_name": null,
      "year": 2018,
      "id_kp": 936288,
      "alternative_id_kp": null,
      "id_imdb": "tt5078618",
      "id_tmdb": 553619,
      "id_world_art": null,
      "token_movie": "dd492e97f5775372e7c44713d240b2",
      "last_season": null,
      "last_episode": null,
      "date": "2021-04-10 18:18:44",
      "country": "США",
      "category": "Фильм",
      "genre": "ужасы",
      "actors": "Julia Beach, Марисса Карпио, Joe Cilio, Шарнель Крик, Коби Фрумер, Alexandra Grunberg, Малкольм Миллс, Nikita Tewani",
      "directors": "Simone Kisiel",
      "producers": "Simone Kisiel",
      "premiere_ru": null,
      "premiere": "2018-10-05",
      "age_restrictions": null,
      "rating_mpaa": null,
      "rating_kp": null,
      "rating_imdb": 5.5,
      "time": "01:06",
      "tagline": "Manners, manicures, and monsters.",
      "poster": "https://kinopoiskapiunofficial.tech/images/posters/kp/936288.jpg",
      "description": null,
      "iframe": "",
      "iframe_trailer": null,
      "category_id": 1,
      "quality": "WEB-DL",
      "translation": "Многоголосый закадровый",
      "translation_iframe": {
        "72": {
          "name": "Многоголосый закадровый",
          "quality": "WEB-DL",
          "iframe": "",
          "adv": true
        }
      }
    },
    {
      "name": "Закон Дарвина",
      "original_name": "Darwins Law",
      "alternative_name": null,
      "year": 2019,
      "id_kp": 1101827,
      "alternative_id_kp": null,
      "id_imdb": "tt7477126",
      "id_tmdb": 619861,
      "id_world_art": null,
      "token_movie": "9e79da8e3673b293eb4503ab5acc5e",
      "last_season": null,
      "last_episode": null,
      "date": "2021-04-10 18:18:12",
      "country": "Германия",
      "category": "Фильм",
      "genre": "боевик",
      "actors": "Патрик Янс, Эстер Маас, Ральф Вилльман, Янош Тиборч, Кларисса Молохер, Sebastian Badenberg, Кристофер Ли Медоуз, Alexandra Bekiou, Viktoria Elisa Juliette Eich, Florian Rednak, Dirk Ehlting, Marc Mirtschin, Мориц Хебелер, Томас Гундерманн, Thomas Schymik, Felix Gabers, Philippo Rednak, Andreas Schlennert, Sebastian Hoff, Stefan Henne",
      "directors": "Маттиас Олоф Ейх",
      "producers": "Маттиас Олоф Ейх",
      "premiere_ru": null,
      "premiere": "2018-07-29",
      "age_restrictions": null,
      "rating_mpaa": null,
      "rating_kp": null,
      "rating_imdb": 6.7,
      "time": "01:27",
      "tagline": null,
      "poster": null,
      "description": null,
      "iframe": "",
      "iframe_trailer": null,
      "category_id": 1,
      "quality": "WEB-DL",
      "translation": "Многоголосый закадровый",
      "translation_iframe": {
        "72": {
          "name": "Многоголосый закадровый",
          "quality": "WEB-DL",
          "iframe": "",
          "adv": true
        }
      }
    },
    {
      "name": "Маки",
      "original_name": "Maki",
      "alternative_name": null,
      "year": 2017,
      "id_kp": 964652,
      "alternative_id_kp": null,
      "id_imdb": "tt5367592",
      "id_tmdb": 654989,
      "id_world_art": null,
      "token_movie": "2f47da2f430d1bd7b031635000a098",
      "last_season": null,
      "last_episode": null,
      "date": "2021-04-10 18:17:40",
      "country": "США, Япония",
      "category": "Фильм",
      "genre": "драма",
      "actors": "Миэко Харада, Джулиан Кихи, Наоми Сандберг, Джина Хираидзуми, Сиори Итикава, Юко Торихара, Адзуми Цуцуи, Тэруаки Акаи, Кана Хатакэяма, Юрика Оно, Даи Исигуро, Бланка Виванкос, Тоси Хамада, Сё Судзуки, Эрина Эда, Джошуа Майкл Пэйн, Патрис Белл, Кэнтаро Кубота, Кодзиро Синохара, Александр Линдквист",
      "directors": "Naghmeh Shirkhan",
      "producers": "Шоре Голпарян, Naghmeh Shirkhan, Никки Арезу Акмаль, Амир Надери, Кертис Смит",
      "premiere_ru": null,
      "premiere": "2017-05-20",
      "age_restrictions": null,
      "rating_mpaa": null,
      "rating_kp": null,
      "rating_imdb": 6.7,
      "time": "01:43",
      "tagline": null,
      "poster": "https://kinopoiskapiunofficial.tech/images/posters/kp/964652.jpg",
      "description": null,
      "iframe": "",
      "iframe_trailer": null,
      "category_id": 1,
      "quality": "WEB-DL",
      "translation": "Многоголосый закадровый",
      "translation_iframe": {
        "72": {
          "name": "Многоголосый закадровый",
          "quality": "WEB-DL",
          "iframe": "",
          "adv": true
        }
      }
    },
    {
      "name": "Горный охотник",
      "original_name": "The Mountain Stalker",
      "alternative_name": null,
      "year": 2018,
      "id_kp": 1192920,
      "alternative_id_kp": null,
      "id_imdb": "tt8810210",
      "id_tmdb": 878414,
      "id_world_art": null,
      "token_movie": "f76c49c45651bf79e0ef8a6401d29c",
      "last_season": null,
      "last_episode": null,
      "date": "2021-04-10 18:17:29",
      "country": "США",
      "category": "Фильм",
      "genre": "триллер",
      "actors": "Roman Brion, Mercedes Alanis, Stephen Winfield, Victor Inman, Eric Morales, Diana Gaona, Faustino Deblas, Meredith Esquivel, Anajaan Zufar Oglana, Master Hughes, Mario Roberto, Panda Butler, Issis Reign",
      "directors": "Master Hughes",
      "producers": "",
      "premiere_ru": null,
      "premiere": "2018-08-07",
      "age_restrictions": null,
      "rating_mpaa": null,
      "rating_kp": null,
      "rating_imdb": 3.4,
      "time": "01:13",
      "tagline": "Never has a more evil killer walked in the forest.",
      "poster": null,
      "description": null,
      "iframe": "",
      "iframe_trailer": null,
      "category_id": 1,
      "quality": "WEB-DL",
      "translation": "Многоголосый закадровый",
      "translation_iframe": {
        "72": {
          "name": "Многоголосый закадровый",
          "quality": "WEB-DL",
          "iframe": "",
          "adv": true
        }
      }
    },
    {
      "name": "Сексуальное безумие: разоблачение",
      "original_name": "Sex Madness Revealed",
      "alternative_name": null,
      "year": 2018,
      "id_kp": 1063479,
      "alternative_id_kp": null,
      "id_imdb": "tt7473034",
      "id_tmdb": 517662,
      "id_world_art": null,
      "token_movie": "acffd8c6a07fa27cd1af70eb9275f1",
      "last_season": null,
      "last_episode": null,
      "date": "2021-04-10 18:17:17",
      "country": "США",
      "category": "Фильм",
      "genre": "комедия, ужасы, фэнтези",
      "actors": "Пэттон Освальт, Роб Забрески, Patrick Cooper",
      "directors": "Тим Кирк",
      "producers": "Тайлер Глодт, Тим Кирк, Родни Ашер, Jay Kirk, David Lawrence, Брэт Вуд",
      "premiere_ru": null,
      "premiere": "2018-04-20",
      "age_restrictions": null,
      "rating_mpaa": null,
      "rating_kp": null,
      "rating_imdb": 5.9,
      "time": "01:07",
      "tagline": "Some people think it's fun to laugh at old movies. Sometimes old movies have the last laugh.",
      "poster": null,
      "description": null,
      "iframe": "",
      "iframe_trailer": null,
      "category_id": 1,
      "quality": "WEB-DL",
      "translation": "Многоголосый закадровый",
      "translation_iframe": {
        "72": {
          "name": "Многоголосый закадровый",
          "quality": "WEB-DL",
          "iframe": "",
          "adv": true
        }
      }
    },
    {
      "name": "Стукач",
      "original_name": "5K1",
      "alternative_name": "Five K One",
      "year": 2018,
      "id_kp": 433142,
      "alternative_id_kp": null,
      "id_imdb": "tt1326219",
      "id_tmdb": 327920,
      "id_world_art": null,
      "token_movie": "583c5e869bcf14f2499fe095e45f9d",
      "last_season": null,
      "last_episode": null,
      "date": "2021-04-10 18:16:57",
      "country": "США",
      "category": "Фильм",
      "genre": "боевик, драма",
      "actors": "Angelo Ashmon, Jason «Kulayd» Clayton, Forty Da Great, Аянна Фуллилов, Биг Херк, Мелвин Джексон мл., Дэниэл Джеффрис, Энтони Джонсон, Quest M.C.O.D.Y., Дэннис МакДермотт, Клифтон Пауэлл, Brandy Tahnora, Кристина Ашер, Якмаус",
      "directors": "Donny Armstrong",
      "producers": "Donny Armstrong, Пол Бритт, Матин Кливз",
      "premiere_ru": null,
      "premiere": "2018-04-22",
      "age_restrictions": null,
      "rating_mpaa": null,
      "rating_kp": null,
      "rating_imdb": 4.7,
      "time": "01:48",
      "tagline": "Urban Drama, Inspired by a true Story",
      "poster": "https://kinopoiskapiunofficial.tech/images/posters/kp/433142.jpg",
      "description": null,
      "iframe": "",
      "iframe_trailer": null,
      "category_id": 1,
      "quality": "WEB-DL",
      "translation": "Многоголосый закадровый",
      "translation_iframe": {
        "72": {
          "name": "Многоголосый закадровый",
          "quality": "WEB-DL",
          "iframe": "",
          "adv": true
        }
      }
    },
    {
      "name": "Атака клоунов",
      "original_name": "Clown Footage",
      "alternative_name": null,
      "year": 2018,
      "id_kp": 1165070,
      "alternative_id_kp": null,
      "id_imdb": "tt8571958",
      "id_tmdb": 588783,
      "id_world_art": null,
      "token_movie": "f70d840fd479da65b638086c0397c2",
      "last_season": null,
      "last_episode": null,
      "date": "2021-04-10 18:16:47",
      "country": "США",
      "category": "Фильм",
      "genre": "ужасы",
      "actors": "Alen Rios, Manny Velazquez",
      "directors": "Manny Velazquez",
      "producers": "Manny Velazquez",
      "premiere_ru": null,
      "premiere": "2018-08-03",
      "age_restrictions": null,
      "rating_mpaa": null,
      "rating_kp": null,
      "rating_imdb": 2.5,
      "time": "01:10",
      "tagline": "The Final Night....",
      "poster": null,
      "description": null,
      "iframe": "",
      "iframe_trailer": null,
      "category_id": 1,
      "quality": "WEB-DL",
      "translation": "Многоголосый закадровый",
      "translation_iframe": {
        "72": {
          "name": "Многоголосый закадровый",
          "quality": "WEB-DL",
          "iframe": "",
          "adv": true
        }
      }
    },
    {
      "name": "Рождество Эйи в Лесу призрачной совы",
      "original_name": "Eia jõulud Tondikakul",
      "alternative_name": null,
      "year": 2018,
      "id_kp": 1211360,
      "alternative_id_kp": null,
      "id_imdb": "tt9261284",
      "id_tmdb": 560716,
      "id_world_art": null,
      "token_movie": "27dbb698264cd02e98e81e4db14d3d",
      "last_season": null,
      "last_episode": null,
      "date": "2021-04-10 18:16:15",
      "country": "Эстония",
      "category": "Фильм",
      "genre": "семейный",
      "actors": "Maria Annus, Роберт Аннус, Annabrith Heinmaa, Марвин Инно, Riho Kütsar, Liis Lemsalu, Тыну Ойя, Siim Oskar Ots, Мярт Пиус, Прийт Пиус, Миртел Пола, Анне Рееманн, Яан Реккор, Paula Rits, Меелис Ряммельд, Тамбет Туйск, Юхан Ульфсак, Приит Войгемаст",
      "directors": "Ану Аун",
      "producers": "Маарио Масинг, Maie Rosmann-Lill",
      "premiere_ru": null,
      "premiere": "2018-11-17",
      "age_restrictions": null,
      "rating_mpaa": null,
      "rating_kp": null,
      "rating_imdb": 7.6,
      "time": "01:30",
      "tagline": null,
      "poster": "https://kinopoiskapiunofficial.tech/images/posters/kp/1211360.jpg",
      "description": "10-летняя девочка Эйа спасает лес за фермой «Призрачной совы» от вырубки жадным владельцем леса Райво.",
      "iframe": "",
      "iframe_trailer": null,
      "category_id": 1,
      "quality": "WEB-DL",
      "translation": "Многоголосый закадровый",
      "translation_iframe": {
        "72": {
          "name": "Многоголосый закадровый",
          "quality": "WEB-DL",
          "iframe": "",
          "adv": true
        }
      }
    },
    {
      "name": "Метеориты",
      "original_name": "Les météorites",
      "alternative_name": null,
      "year": 2018,
      "id_kp": 1197591,
      "alternative_id_kp": null,
      "id_imdb": "tt8948974",
      "id_tmdb": 546549,
      "id_world_art": null,
      "token_movie": "b685a149d9ec125902397cf03c57d2",
      "last_season": null,
      "last_episode": null,
      "date": "2021-04-10 18:15:54",
      "country": "Франция",
      "category": "Фильм",
      "genre": "драма, мелодрама",
      "actors": "Зеа Дюпрез, Билаль Агаб, Умайма Лиамури, Натан ле Грасье, Рози Броннер, Камилль Линьон, Шарль Буске, Филипп Гонзалес, Морган Гизелинк, Осеан Лопес, Марион Буте, Oualid Ait Barrazouk, Brahim Kharrazi, Ouladi Kharrazi, Olivier Pouget, Justin Corraze, Anthony Ortiz, David Daveque, Louis Daveque, Kelly Bolot",
      "directors": "Ромен Лагуна",
      "producers": "Шарль Филипп, Люсиль Рик",
      "premiere_ru": null,
      "premiere": "2018-09-23",
      "age_restrictions": null,
      "rating_mpaa": null,
      "rating_kp": null,
      "rating_imdb": 5.7,
      "time": "01:25",
      "tagline": null,
      "poster": "https://kinopoiskapiunofficial.tech/images/posters/kp/1197591.jpg",
      "description": "Нина, 16-летняя девочка, мечтает о приключениях. Она проводит лето между своей деревней на юге Франции и тематическим парком, где она работает. Незадолго до встречи с Морадом, подростком из алжирской семьи, живущим по соседству, Нина видит падающий с неба метеорит, который, кажется, только она может видеть как предзнаменование чего-то.",
      "iframe": "",
      "iframe_trailer": null,
      "category_id": 1,
      "quality": "WEB-DL",
      "translation": "Многоголосый закадровый",
      "translation_iframe": {
        "72": {
          "name": "Многоголосый закадровый",
          "quality": "WEB-DL",
          "iframe": "",
          "adv": true
        }
      }
    },
    {
      "name": "Зверь в чаще",
      "original_name": "The Beast in the Jungle",
      "alternative_name": null,
      "year": 2019,
      "id_kp": 1058495,
      "alternative_id_kp": null,
      "id_imdb": "tt6766376",
      "id_tmdb": 568360,
      "id_world_art": null,
      "token_movie": "6d2d302fad59329bd7889d131b181d",
      "last_season": null,
      "last_episode": null,
      "date": "2021-04-10 18:15:43",
      "country": "Нидерланды",
      "category": "Фильм",
      "genre": "драма",
      "actors": "Sarah Reynolds, Dane Hurst, Клер Джонстон, Лариса Фабер, Jerome Burelbach, Джулиан Нест, Сильвия Камарда, Tommy Schlesser, Элизабет Йоханнесдоттир, Жан-Марк Андре, Christian Bronchart, Joe Gales, Микаэль Кахья, Софи Ланжевен",
      "directors": "Clara van Gool",
      "producers": "Ганс де Вульф, Ханнеке Нинс, Александр Думрайхер-Ивансеану, Ohna Falby, Андре Фецер, Бади Минк, Isabelle Moree, Karina van Tol, Марианн ван Хардевельд",
      "premiere_ru": null,
      "premiere": "2019-01-27",
      "age_restrictions": null,
      "rating_mpaa": null,
      "rating_kp": null,
      "rating_imdb": 5.2,
      "time": "01:27",
      "tagline": "The story of a man in whose life precisely nothing was to happen...",
      "poster": null,
      "description": null,
      "iframe": "",
      "iframe_trailer": null,
      "category_id": 1,
      "quality": "WEB-DL",
      "translation": "Многоголосый закадровый",
      "translation_iframe": {
        "72": {
          "name": "Многоголосый закадровый",
          "quality": "WEB-DL",
          "iframe": "",
          "adv": true
        }
      }
    },
    {
      "name": "Красная Ярмарка",
      "original_name": "Red Fair",
      "alternative_name": null,
      "year": 2019,
      "id_kp": null,
      "alternative_id_kp": null,
      "id_imdb": null,
      "id_tmdb": null,
      "id_world_art": null,
      "token_movie": "b1b57a54bc9138e6b659a7bfa4eeec",
      "last_season": null,
      "last_episode": null,
      "date": "2021-04-10 18:15:28",
      "country": null,
      "category": "Фильм",
      "genre": null,
      "actors": null,
      "directors": null,
      "producers": null,
      "premiere_ru": null,
      "premiere": null,
      "age_restrictions": null,
      "rating_mpaa": null,
      "rating_kp": null,
      "rating_imdb": null,
      "time": null,
      "tagline": null,
      "poster": null,
      "description": null,
      "iframe": "",
      "iframe_trailer": null,
      "category_id": 1,
      "quality": "WEB-DL",
      "translation": "Многоголосый закадровый",
      "translation_iframe": {
        "72": {
          "name": "Многоголосый закадровый",
          "quality": "WEB-DL",
          "iframe": "",
          "adv": true
        }
      }
    },
    {
      "name": "Гусбой",
      "original_name": "Gooseboy",
      "alternative_name": null,
      "year": 2019,
      "id_kp": 1181953,
      "alternative_id_kp": null,
      "id_imdb": "tt8857368",
      "id_tmdb": 592397,
      "id_world_art": null,
      "token_movie": "2e8eedadcf644f445ac93e3e5fd471",
      "last_season": null,
      "last_episode": null,
      "date": "2021-04-10 18:15:09",
      "country": "Дания",
      "category": "Фильм",
      "genre": "комедия, семейный",
      "actors": "Расмус Бьерг, Николас Бро, Дарио Кампеотто, Чанг Иль Ким, Мари Далсгор, Mads Geertsen, Кэролайн Хендерсон, Klumben, Сёрен Маллинг, Фрида Луна Росвалль Маттсон, Pharfar, Стин Расмуссен, Thomas Refslund Ravn, Ширли Хаим, Ульрих Томсен, Michael Wikke",
      "directors": "Стин Расмуссен, Michael Wikke",
      "producers": "Julie Rix Bomholt, Миа Эльвстрем Мюрольф, Шандор Папп, Ларс Бредо Рабек, Энн Рудбэк, Signe Vinther, Anna Malmkjær Willumsen",
      "premiere_ru": null,
      "premiere": "2019-10-03",
      "age_restrictions": null,
      "rating_mpaa": null,
      "rating_kp": null,
      "rating_imdb": 6.3,
      "time": "01:27",
      "tagline": null,
      "poster": null,
      "description": null,
      "iframe": "",
      "iframe_trailer": null,
      "category_id": 1,
      "quality": "WEB-DL",
      "translation": "Многоголосый закадровый",
      "translation_iframe": {
        "72": {
          "name": "Многоголосый закадровый",
          "quality": "WEB-DL",
          "iframe": "",
          "adv": true
        }
      }
    },
    {
      "name": "Тимми Фейл: Допущены ошибки",
      "original_name": "Timmy Failure: Mistakes Were Made",
      "alternative_name": null,
      "year": 2020,
      "id_kp": 1094990,
      "alternative_id_kp": null,
      "id_imdb": "tt6820324",
      "id_tmdb": 550440,
      "id_world_art": null,
      "token_movie": "cfe10b067a67d288b96507e706e726",
      "last_season": null,
      "last_episode": null,
      "date": "2021-04-10 18:14:38",
      "country": "США",
      "category": "Фильм",
      "genre": "детектив, комедия, приключения",
      "actors": "Уинслоу Фегли, Офелия Ловибонд, Уоллес Шоун, Крэйг Робинсон, Кайл Борнхаймер, Аи-Чан Кэрриэр, Хлоя Коулмэн, Kei, Caitlin Weierhauser, Alan H. King, Сантьяго Визажа, Руби Матенко, Sheldon Hanai, Rachel Bentzen, Дэниэл Чай, Кристофер Мартинес, Роб Кэмпбелл, Николь Энтони, Кимберли Ховард, Lucca Cecil",
      "directors": "Том МакКарти",
      "producers": "Том МакКарти, Джеймс Уитакер, Майкл Бедерман, Taylor Chestnut, Кейт Черчилль, Александр Досталь",
      "premiere_ru": null,
      "premiere": "2020-01-25",
      "age_restrictions": null,
      "rating_mpaa": "pg",
      "rating_kp": 5.5,
      "rating_imdb": 6.1,
      "time": "01:39",
      "tagline": null,
      "poster": "https://kinopoiskapiunofficial.tech/images/posters/kp/1094990.jpg",
      "description": "11-летний мальчик, убежденный, что он лучший детектив в городе, управляет своим агентством и распутывает различные дела вместе с приятелем — гигантским полярным медведем.",
      "iframe": "",
      "iframe_trailer": null,
      "category_id": 1,
      "quality": "WEB-DL",
      "translation": "Многоголосый закадровый",
      "translation_iframe": {
        "72": {
          "name": "Многоголосый закадровый",
          "quality": "WEB-DL",
          "iframe": "",
          "adv": true
        }
      }
    },
    {
      "name": "Пара на День святого Валентина",
      "original_name": "A Valentine's Match",
      "alternative_name": null,
      "year": 2020,
      "id_kp": 1331128,
      "alternative_id_kp": null,
      "id_imdb": "tt11274306",
      "id_tmdb": 661331,
      "id_world_art": null,
      "token_movie": "b6ba117575638022c97fa76d146045",
      "last_season": null,
      "last_episode": null,
      "date": "2021-04-10 18:14:10",
      "country": "Канада, США",
      "category": "Фильм",
      "genre": "драма, мелодрама",
      "actors": "Бетани Джои Ленц, Люк МакФарлейн, Мэри-Маргарет Хьюмс, Карен Крупер, Девон Александр, Кэйтлин Кромуэлл, Марко Граззини, Кристина Ястржембска, Кен Тремблетт, Грег Роджерс, Донни Лукас, Клод Нолтон, Тревор Лернер, Чад Райли, Жасмин Лукуку, Донна Суарес, Дин Хинчи, Стиви Джексон, Лаура Эдкин",
      "directors": "Кристи Уилл",
      "producers": "Робин Винер, Сэмми Астане, Винс Бальцано, Сьюзи Кревой, Доран Чандлер, Роб Грант, Эрик Жарбо, Брэд Кревой, Кевин Лисон",
      "premiere_ru": null,
      "premiere": "2020-02-01",
      "age_restrictions": null,
      "rating_mpaa": null,
      "rating_kp": null,
      "rating_imdb": 6.8,
      "time": "01:22",
      "tagline": null,
      "poster": "https://kinopoiskapiunofficial.tech/images/posters/kp/1331128.jpg",
      "description": "Натали, успешная телеведущая, возвращается в родной город спустя долгое время. Там она встречает бывшего жениха, с которым ей предстоит заниматься организацией фестиваля в честь Дня святого Валентина. Они все ещё испытывают чувства друг к другу, однако у Натали есть парень.",
      "iframe": "",
      "iframe_trailer": null,
      "category_id": 1,
      "quality": "HDTV",
      "translation": "Многоголосый закадровый",
      "translation_iframe": {
        "72": {
          "name": "Многоголосый закадровый",
          "quality": "HDTV",
          "iframe": "",
          "adv": true
        }
      }
    },
    {
      "name": "Другая сторона",
      "original_name": "Öteki Taraf",
      "alternative_name": null,
      "year": 2017,
      "id_kp": 1018563,
      "alternative_id_kp": null,
      "id_imdb": "tt6213036",
      "id_tmdb": 477315,
      "id_world_art": null,
      "token_movie": "8edb056411ad67e2680205c596ab6d",
      "last_season": null,
      "last_episode": null,
      "date": "2021-04-10 18:12:41",
      "country": "Турция",
      "category": "Фильм",
      "genre": "драма, триллер",
      "actors": "Озджан Дениз, Мерьем Узерли, Аслы Энвер, Osman Wöber, Бурчин Бирбен, Айтен Унджуоглу, Sena Çakir",
      "directors": "Озджан Дениз",
      "producers": "Кристиан Конти",
      "premiere_ru": null,
      "premiere": "2017-12-08",
      "age_restrictions": null,
      "rating_mpaa": null,
      "rating_kp": 6.4,
      "rating_imdb": 6.1,
      "time": "01:39",
      "tagline": null,
      "poster": "https://kinopoiskapiunofficial.tech/images/posters/kp/1018563.jpg",
      "description": null,
      "iframe": "",
      "iframe_trailer": null,
      "category_id": 1,
      "quality": "WEB-DL",
      "translation": "Многоголосый закадровый",
      "translation_iframe": {
        "72": {
          "name": "Многоголосый закадровый",
          "quality": "WEB-DL",
          "iframe": "",
          "adv": true
        }
      }
    },
    {
      "name": "Доброе имя",
      "original_name": null,
      "alternative_name": null,
      "year": 2014,
      "id_kp": 840043,
      "alternative_id_kp": null,
      "id_imdb": null,
      "id_tmdb": null,
      "id_world_art": null,
      "token_movie": "0096ff4d0b3f169a771c75b69f26b6",
      "last_season": 1,
      "last_episode": 12,
      "date": "2021-04-10 17:35:43",
      "country": "Россия",
      "category": "Сериал",
      "genre": "детектив, мелодрама",
      "actors": "Марат Башаров, Екатерина Вуличенко, Константин Воробьёв, Павел Харланчук, Василий Козлов, Анатолий Голуб, Иван Мацкевич, Георгий Малявский, Анастасия Аравина, Георгий Петренко, Александр Суцковер, Андрей Душечкин, Зоя Белохвостик, Ольга Бурлакова, Дмитрий Мухин, Елена Родак, Татьяна Калих, Дмитрий Абазовик, Марина Денисова, Андрей Милюхин",
      "directors": "Александр Аравин",
      "producers": "Юрий Сапронов, Евгения Цицина, Регина Петрова, Константин Дыдышко, Мария Перекатова, Ирина Прохорова, Александр Самойленко, Давид Ткебучава",
      "premiere_ru": "2014-05-19",
      "premiere": "2014-05-12",
      "age_restrictions": 16,
      "rating_mpaa": null,
      "rating_kp": 4.8,
      "rating_imdb": null,
      "time": "00:45",
      "tagline": null,
      "poster": "https://kinopoiskapiunofficial.tech/images/posters/kp/840043.jpg",
      "description": "Антон Добряков, в прошлом капитан полиции, работает частным детективом. Благодаря своим незаурядным сыскным способностям, он раскрывает одно дело за другим. Однако Добряков с радостью вернулся бы в полицию. Проблема в том, что Добряков враждует с начальником ОВД Шубиным, после драки с которым он и уволился из органов. Добряков подозревает Шубина в покушении на Ивана Крестова, год назад руководившего этим ОВД.\n\rЗоя, жена Антона, тоже работает в правоохранительных органах. Обоюдная ревность, неуемная страсть Добрякова к работе и взбалмошный характер Зои делают их совместную жизнь невыносимой. Они любят друг друга, но постоянно находятся на грани развода.\n\rЗою и Добрякова объединяет общая потеря. Несколько лет назад прямо у дверей ОВД был убит отец Зои, полковник Свиридов. Для Добрякова найти убийц Свиридова – главная задача. И каждая серия приближает его к заказчику этого убийства.",
      "iframe": "",
      "iframe_trailer": null,
      "category_id": 2,
      "seasons_count": 1,
      "seasons": {
        "1": {
          "iframe": "",
          "season": 1,
          "episodes": {
            "12": {
              "iframe": "",
              "episode": 12,
              "translation": {
                "82": {
                  "translation": "Не требуется",
                  "quality": "WEB-DL",
                  "iframe": ""
                }
              }
            },
            "11": {
              "iframe": "",
              "episode": 11,
              "translation": {
                "82": {
                  "translation": "Не требуется",
                  "quality": "WEB-DL",
                  "iframe": ""
                }
              }
            },
            "10": {
              "iframe": "",
              "episode": 10,
              "translation": {
                "82": {
                  "translation": "Не требуется",
                  "quality": "WEB-DL",
                  "iframe": ""
                }
              }
            },
            "9": {
              "iframe": "",
              "episode": 9,
              "translation": {
                "82": {
                  "translation": "Не требуется",
                  "quality": "WEB-DL",
                  "iframe": ""
                }
              }
            },
            "8": {
              "iframe": "",
              "episode": 8,
              "translation": {
                "82": {
                  "translation": "Не требуется",
                  "quality": "WEB-DL",
                  "iframe": ""
                }
              }
            },
            "7": {
              "iframe": "",
              "episode": 7,
              "translation": {
                "82": {
                  "translation": "Не требуется",
                  "quality": "WEB-DL",
                  "iframe": ""
                }
              }
            },
            "6": {
              "iframe": "",
              "episode": 6,
              "translation": {
                "82": {
                  "translation": "Не требуется",
                  "quality": "WEB-DL",
                  "iframe": ""
                }
              }
            },
            "5": {
              "iframe": "",
              "episode": 5,
              "translation": {
                "82": {
                  "translation": "Не требуется",
                  "quality": "WEB-DL",
                  "iframe": ""
                }
              }
            },
            "4": {
              "iframe": "",
              "episode": 4,
              "translation": {
                "82": {
                  "translation": "Не требуется",
                  "quality": "WEB-DL",
                  "iframe": ""
                }
              }
            },
            "3": {
              "iframe": "",
              "episode": 3,
              "translation": {
                "82": {
                  "translation": "Не требуется",
                  "quality": "WEB-DL",
                  "iframe": ""
                }
              }
            },
            "2": {
              "iframe": "",
              "episode": 2,
              "translation": {
                "82": {
                  "translation": "Не требуется",
                  "quality": "WEB-DL",
                  "iframe": ""
                }
              }
            },
            "1": {
              "iframe": "",
              "episode": 1,
              "translation": {
                "82": {
                  "translation": "Не требуется",
                  "quality": "WEB-DL",
                  "iframe": ""
                }
              }
            }
          }
        }
      },
      "quality": "WEB-DL",
      "translation": "Не требуется",
      "translation_iframe": {
        "82": {
          "name": "Не требуется",
          "quality": "WEB-DL",
          "iframe": "",
          "adv": false
        }
      }
    },
    {
      "name": "Что сделал Джек?",
      "original_name": "What Did Jack Do?",
      "alternative_name": null,
      "year": 2017,
      "id_kp": 1338431,
      "alternative_id_kp": null,
      "id_imdb": "tt11644096",
      "id_tmdb": 528491,
      "id_world_art": null,
      "token_movie": "0cf6d27407ad69217fc7ecb82e8117",
      "last_season": null,
      "last_episode": null,
      "date": "2021-04-10 17:32:06",
      "country": "США",
      "category": "Фильм",
      "genre": "короткометражка, триллер, фэнтези",
      "actors": "Джек Крус, Дэвид Линч, Toototabon, Эмили Стоуфл",
      "directors": "Дэвид Линч",
      "producers": "Сабрина С. Сазерленд",
      "premiere_ru": null,
      "premiere": "2017-11-08",
      "age_restrictions": null,
      "rating_mpaa": null,
      "rating_kp": 7.1,
      "rating_imdb": 6.5,
      "time": "00:17",
      "tagline": null,
      "poster": "https://kinopoiskapiunofficial.tech/images/posters/kp/1338431.jpg",
      "description": "Сюжет повествует о допросе мартышки, обвиненной в убийстве.",
      "iframe": "",
      "iframe_trailer": null,
      "category_id": 1,
      "quality": "WEB-DL",
      "translation": "Многоголосый закадровый",
      "translation_iframe": {
        "72": {
          "name": "Многоголосый закадровый",
          "quality": "WEB-DL",
          "iframe": "",
          "adv": true
        }
      }
    },
    {
      "name": "Я бросил тебе вызов! Правда или действие 5",
      "original_name": "I Dared You! Truth or Dare Part 5",
      "alternative_name": null,
      "year": 2017,
      "id_kp": 929020,
      "alternative_id_kp": null,
      "id_imdb": "tt4940094",
      "id_tmdb": 487187,
      "id_world_art": null,
      "token_movie": "41d6eae5c3a90f1d3b1c3c32067f12",
      "last_season": null,
      "last_episode": null,
      "date": "2021-04-10 17:31:50",
      "country": "США",
      "category": "Фильм",
      "genre": "ужасы",
      "actors": "Скотт Тепперман, Джоэль Д. Винкооп, Джим О’Риэр, Тим Риттер, Эшли Линн Капуто, Джоэнн Мариньо, Cayt Feinics, Билли В. Блэкуэлл, Eric Danger Dionne, Боб Глэйзер, Тадеус Игнасио, Хезер Прайс, Тодд Мартин, M. Catherine Wynkoop, Jimmie Nassen, Эрнест Дуглас Николс, Дэймон Проктор, Stoney Lawrentz, Trish Erickson-Martin, Shawn McMahon",
      "directors": "Тим Риттер, Скотт Тепперман",
      "producers": "Скотт Тепперман",
      "premiere_ru": null,
      "premiere": null,
      "age_restrictions": null,
      "rating_mpaa": null,
      "rating_kp": null,
      "rating_imdb": null,
      "time": "01:30",
      "tagline": "In 1986, a cult-classic was born. This fall, the madness gets critical.",
      "poster": null,
      "description": null,
      "iframe": "",
      "iframe_trailer": null,
      "category_id": 1,
      "quality": "WEB-DL",
      "translation": "Многоголосый закадровый",
      "translation_iframe": {
        "72": {
          "name": "Многоголосый закадровый",
          "quality": "WEB-DL",
          "iframe": "",
          "adv": true
        }
      }
    },
    {
      "name": "Обещание Астрид",
      "original_name": "A Promise To Astrid",
      "alternative_name": null,
      "year": 2019,
      "id_kp": 1201448,
      "alternative_id_kp": null,
      "id_imdb": "tt9125380",
      "id_tmdb": 645833,
      "id_world_art": null,
      "token_movie": "4cce6af4974a0f6f53d6d422cf4e65",
      "last_season": null,
      "last_episode": null,
      "date": "2021-04-10 17:31:06",
      "country": "США",
      "category": "Фильм",
      "genre": "драма",
      "actors": "Дин Кэйн, JoAnn F. Peterson, Джереми Гладен, Luba Hansen, Ричи Асеведо, Carson Campbell, Gabby Christie, Maizze Christie, Barry Michael Dailey, Donna Elsey, Тимоти Э. Гудвин, Jesse L. Green, Emma Hansberry, Grace Hansberry, Madison Hansberry, Keith Hastman, Kathy Jones, Barb Knicely, Phuong Kubacki, A.T. Lantz",
      "directors": "Джейсон Кэмпбелл, Гари Ли Винсент",
      "producers": "Джейсон Кэмпбелл, Mike Tourville",
      "premiere_ru": null,
      "premiere": "2019-05-09",
      "age_restrictions": null,
      "rating_mpaa": null,
      "rating_kp": null,
      "rating_imdb": 5.5,
      "time": "01:28",
      "tagline": null,
      "poster": "https://kinopoiskapiunofficial.tech/images/posters/kp/1201448.jpg",
      "description": "История о женщине, которая, делая добрые дела, изменила жизнь целого сообщества.",
      "iframe": "",
      "iframe_trailer": null,
      "category_id": 1,
      "quality": "WEB-DL",
      "translation": "Многоголосый закадровый",
      "translation_iframe": {
        "72": {
          "name": "Многоголосый закадровый",
          "quality": "WEB-DL",
          "iframe": "",
          "adv": true
        }
      }
    },
    {
      "name": "Колокольчик",
      "original_name": "Bellbird",
      "alternative_name": null,
      "year": 2019,
      "id_kp": 1209692,
      "alternative_id_kp": null,
      "id_imdb": "tt9170352",
      "id_tmdb": 601204,
      "id_world_art": null,
      "token_movie": "194ad0775f97e494c2d3b0129bba17",
      "last_season": null,
      "last_episode": null,
      "date": "2021-04-10 17:30:42",
      "country": "Новая Зеландия",
      "category": "Фильм",
      "genre": "драма, комедия",
      "actors": "Маршалл Напье, Энни Уиттл, Коэн Холлоуэй, Рэйчел Хаус, Stephen Tamarapa, Кип Чэпман, Саймон Ферри, Jason Hodzelmans, Бри Питерс, Jeremy K. Hill, Аарон Джексон, Ainzlee Semeno, Шэйн Редфорд, Angela Radford, Edith Gallichan-Stewart, Francis Gallichan-Stewart, Simon Cauty, Waimarie McQueen, Mick Gibson, Kahukura Retimana",
      "directors": "Hamish Bennett",
      "producers": "Катрин Фицджералд, Орландо Стюарт",
      "premiere_ru": null,
      "premiere": "2019-06-11",
      "age_restrictions": null,
      "rating_mpaa": null,
      "rating_kp": null,
      "rating_imdb": 6.5,
      "time": "01:36",
      "tagline": null,
      "poster": "https://kinopoiskapiunofficial.tech/images/posters/kp/1209692.jpg",
      "description": null,
      "iframe": "",
      "iframe_trailer": null,
      "category_id": 1,
      "quality": "WEB-DL",
      "translation": "Многоголосый закадровый",
      "translation_iframe": {
        "72": {
          "name": "Многоголосый закадровый",
          "quality": "WEB-DL",
          "iframe": "",
          "adv": true
        }
      }
    },
    {
      "name": "Крипта",
      "original_name": "Cripta",
      "alternative_name": null,
      "year": 2019,
      "id_kp": null,
      "alternative_id_kp": null,
      "id_imdb": null,
      "id_tmdb": null,
      "id_world_art": null,
      "token_movie": "91910e041ad7c8235a5c69bfd293eb",
      "last_season": null,
      "last_episode": null,
      "date": "2021-04-10 17:30:22",
      "country": null,
      "category": "Фильм",
      "genre": null,
      "actors": null,
      "directors": null,
      "producers": null,
      "premiere_ru": null,
      "premiere": null,
      "age_restrictions": null,
      "rating_mpaa": null,
      "rating_kp": null,
      "rating_imdb": null,
      "time": null,
      "tagline": null,
      "poster": null,
      "description": null,
      "iframe": "",
      "iframe_trailer": null,
      "category_id": 1,
      "quality": "WEB-DL",
      "translation": "Многоголосый закадровый",
      "translation_iframe": {
        "72": {
          "name": "Многоголосый закадровый",
          "quality": "WEB-DL",
          "iframe": "",
          "adv": true
        }
      }
    },
    {
      "name": "Астрономия",
      "original_name": "Cheonmun: haneule munneunda",
      "alternative_name": null,
      "year": 2019,
      "id_kp": 1167684,
      "alternative_id_kp": null,
      "id_imdb": "tt11498038",
      "id_tmdb": 569267,
      "id_world_art": null,
      "token_movie": "bc0b4dc3f4bf747ef918b9184deced",
      "last_season": null,
      "last_episode": null,
      "date": "2021-04-10 17:29:07",
      "country": "Корея Южная",
      "category": "Фильм",
      "genre": "биография, драма, история",
      "actors": "Хан Сок-кю, Чхве Мин-сик, Щин Гу, Ким Хон-пха, Хо Джун-хо, Ким Тхэ-у, Лим Вон-хи, Ким Вон-хэ, О Гван-нок, Пак Сон-хун, Чон Ё-бин, Ким Сын-хун, Пэ Джэ-ги, Ли Джун-ок, Юн Джэ-мун, Мин Гён-джин, Ли Дон-ён, Чхве Джэ-соп, Ли Со-хван, Хён Бон-щик",
      "directors": "Хо Джин-хо",
      "producers": "Ким Вон-гук, Ким Чхоль-ён",
      "premiere_ru": null,
      "premiere": "2019-12-26",
      "age_restrictions": null,
      "rating_mpaa": null,
      "rating_kp": null,
      "rating_imdb": 6.6,
      "time": "02:12",
      "tagline": null,
      "poster": "https://kinopoiskapiunofficial.tech/images/posters/kp/1167684.jpg",
      "description": "Чосон, XV век. Чан Ён-щиль имел низкое происхождение и был рабом, но, увидев его невероятные способности к науками и инженерному мастерству, монарх Седжон даровал ему свободу и назначил учёным 5-го ранга. Поскольку Чосон вынужденно пользовался неподходящим для местных условий китайским сельскохозяйственным календарём, Седжон решает составить свой календарь, а для этого необходимы астрономические измерительные приборы. Ответственным за создание первой корейской армиллярной сферы назначается Чан Ён-щиль.",
      "iframe": "",
      "iframe_trailer": null,
      "category_id": 1,
      "quality": "WEB-DL",
      "translation": "Многоголосый закадровый",
      "translation_iframe": {
        "72": {
          "name": "Многоголосый закадровый",
          "quality": "WEB-DL",
          "iframe": "",
          "adv": true
        }
      }
    },
    {
      "name": "Уловки страсти: Девушка встречает парня",
      "original_name": "Hotto Gimikku: Garu Mitsu Boi",
      "alternative_name": null,
      "year": 2019,
      "id_kp": 1253961,
      "alternative_id_kp": null,
      "id_imdb": "tt10061256",
      "id_tmdb": 602797,
      "id_world_art": null,
      "token_movie": "569fc00c811afd9956b55ca9f69546",
      "last_season": null,
      "last_episode": null,
      "date": "2021-04-10 17:28:24",
      "country": "Япония",
      "category": "Фильм",
      "genre": "мелодрама",
      "actors": "Миона Хори, Хироя Симидзу, Мидзуки Итагаки, Сётаро Мамия, Каисэи Камимура, Хиёри Сакурада, Рихо Ёсиока",
      "directors": "Юки Ямато",
      "producers": "",
      "premiere_ru": null,
      "premiere": "2019-06-20",
      "age_restrictions": null,
      "rating_mpaa": null,
      "rating_kp": null,
      "rating_imdb": 4.4,
      "time": "01:59",
      "tagline": null,
      "poster": "https://kinopoiskapiunofficial.tech/images/posters/kp/1253961.jpg",
      "description": null,
      "iframe": "",
      "iframe_trailer": null,
      "category_id": 1,
      "quality": "WEB-DL",
      "translation": "Многоголосый закадровый",
      "translation_iframe": {
        "72": {
          "name": "Многоголосый закадровый",
          "quality": "WEB-DL",
          "iframe": "",
          "adv": true
        }
      }
    },
    {
      "name": "Я, толстуха",
      "original_name": "Moi, Grosse",
      "alternative_name": null,
      "year": 2019,
      "id_kp": 1273124,
      "alternative_id_kp": null,
      "id_imdb": "tt10350736",
      "id_tmdb": null,
      "id_world_art": null,
      "token_movie": "e409df16c7c3d6cc3ec15a1471917f",
      "last_season": null,
      "last_episode": null,
      "date": "2021-04-10 17:28:03",
      "country": "Франция",
      "category": "Фильм",
      "genre": "драма, комедия",
      "actors": "Juliette Katz, Жюли Деларме, Антуан Дюлери, Эвелин Буикс, Yelena Polizzi, Christopher Bayemi, Камилла Жапи, Matthieu Sampeur, Саадиа Бентайеб, Жан-Филипп Пюмартин, Марина Томе, Marina Carrère d'Encausse, Лор Эннекуар, Франк Меркадаль, Жан-Батист Шельмердин, Мэтью Барбет, Lola Cès, Gabrielle Deydier, Mathilde Wambergue, Мартен Дакен",
      "directors": "Мюриэлль Магеллан",
      "producers": "Лоуренс Бачман",
      "premiere_ru": null,
      "premiere": "2019-05-15",
      "age_restrictions": null,
      "rating_mpaa": null,
      "rating_kp": null,
      "rating_imdb": 6.3,
      "time": "01:27",
      "tagline": null,
      "poster": null,
      "description": null,
      "iframe": "",
      "iframe_trailer": null,
      "category_id": 1,
      "quality": "HDTV",
      "translation": "Многоголосый закадровый",
      "translation_iframe": {
        "72": {
          "name": "Многоголосый закадровый",
          "quality": "HDTV",
          "iframe": "",
          "adv": true
        }
      }
    },
    {
      "name": "В ожидании Ани",
      "original_name": "Waiting for Anya",
      "alternative_name": null,
      "year": 2020,
      "id_kp": 1057104,
      "alternative_id_kp": null,
      "id_imdb": "tt7095476",
      "id_tmdb": 525428,
      "id_world_art": null,
      "token_movie": "44678e8fdb81573a92638a2d799c1f",
      "last_season": null,
      "last_episode": null,
      "date": "2021-04-10 17:27:45",
      "country": "Бельгия, Великобритания",
      "category": "Фильм",
      "genre": "военный, драма, триллер",
      "actors": "Ноа Шнапп, Томас Кречман, Фредерик Шмидт, Томас Лемаркус, Жиль Марини, Эльза Зильберштейн, Жозефин де ла Буме, Сэди Фрост, Жан Рено, Анжелика Хьюстон, Declan Cole, Enola Izquierdo Cicuendez, Amandine Rose, Mathys Gallet-Lartigue, Лорен Педебернар, Уильям Абади, Николас Роу, Жан-Франсуа Бальмер, Dolma Raisson, Урс Рехн",
      "directors": "Бен Куксон",
      "producers": "Jwanwat Ahriyavraromp, Танназ Аниси, Радж Авасти, Кирсти Белл, Джон Бернард, Аластер Берлинэм, Ekkasitha Chalermrattawongz, Фин Глинн, Хэтти Глинн",
      "premiere_ru": null,
      "premiere": "2020-01-16",
      "age_restrictions": null,
      "rating_mpaa": null,
      "rating_kp": null,
      "rating_imdb": 6,
      "time": "01:49",
      "tagline": "War Has No Escape",
      "poster": null,
      "description": "История о небольшой горной французской деревушке, оккупированной немцами, жители которой помогают прятать детей-евреев и переправлять их в Испанию.",
      "iframe": "",
      "iframe_trailer": null,
      "category_id": 1,
      "quality": "WEB-DL",
      "translation": "Многоголосый закадровый",
      "translation_iframe": {
        "72": {
          "name": "Многоголосый закадровый",
          "quality": "WEB-DL",
          "iframe": "",
          "adv": true
        }
      }
    },
    {
      "name": "Два/один",
      "original_name": "Two/One",
      "alternative_name": null,
      "year": 2019,
      "id_kp": 1052920,
      "alternative_id_kp": null,
      "id_imdb": "tt3842684",
      "id_tmdb": 494972,
      "id_world_art": null,
      "token_movie": "dbb3ee7f968d8e688c6b17a392b126",
      "last_season": null,
      "last_episode": null,
      "date": "2021-04-10 17:25:28",
      "country": "Аргентина, Великобритания, Канада, Китай",
      "category": "Фильм",
      "genre": "драма",
      "actors": "Бойд Холбрук, Бо Бриджес, Анна Ван Хуфт, Чжу Чжу, Мэдди Филлипс, Джейн МакГрегор, Эшли Росс, Кэндас Черчилль, Рэймонд Ма, Юки Морита, Сун Ян, Брайан Кэлверт, Риун Гарнер, Emma Yi",
      "directors": "Juan Cabral",
      "producers": "Крис Кларк, Флора Фернандес-Маренго, Мечи Тарелли, Дэвид Валло",
      "premiere_ru": null,
      "premiere": "2019-04-28",
      "age_restrictions": null,
      "rating_mpaa": null,
      "rating_kp": null,
      "rating_imdb": 6,
      "time": "01:40",
      "tagline": "What if your life was someone else's dream?",
      "poster": "https://kinopoiskapiunofficial.tech/images/posters/kp/1052920.jpg",
      "description": null,
      "iframe": "",
      "iframe_trailer": null,
      "category_id": 1,
      "quality": "WEB-DL",
      "translation": "Многоголосый закадровый",
      "translation_iframe": {
        "72": {
          "name": "Многоголосый закадровый",
          "quality": "WEB-DL",
          "iframe": "",
          "adv": true
        }
      }
    },
    {
      "name": "Прямой Эфир",
      "original_name": "Live Stream",
      "alternative_name": null,
      "year": 2019,
      "id_kp": null,
      "alternative_id_kp": null,
      "id_imdb": "tt11303440",
      "id_tmdb": 657273,
      "id_world_art": null,
      "token_movie": "8526156428eedda5cac1f99286a86e",
      "last_season": null,
      "last_episode": null,
      "date": "2021-04-10 17:24:57",
      "country": null,
      "category": "Фильм",
      "genre": null,
      "actors": null,
      "directors": null,
      "producers": null,
      "premiere_ru": null,
      "premiere": null,
      "age_restrictions": null,
      "rating_mpaa": null,
      "rating_kp": null,
      "rating_imdb": null,
      "time": null,
      "tagline": null,
      "poster": null,
      "description": null,
      "iframe": "",
      "iframe_trailer": null,
      "category_id": 1,
      "quality": "BDRip",
      "translation": "Многоголосый закадровый",
      "translation_iframe": {
        "72": {
          "name": "Многоголосый закадровый",
          "quality": "BDRip",
          "iframe": "",
          "adv": true
        }
      }
    }
  ]
}
